{"created": 1777979557.4709215, "duration": 0.025404691696166992, "exitcode": 0, "root": "/home/piyush/Desktop/devops_project/gitcheck", "environment": {}, "summary": {"passed": 23, "total": 23, "collected": 23}, "collectors": [{"nodeid": "", "outcome": "passed", "result": [{"nodeid": "tests", "type": "Dir"}]}, {"nodeid": "tests/test_malicious_scenarios.py::TestSecretScanner", "outcome": "passed", "result": [{"nodeid": "tests/test_malicious_scenarios.py::TestSecretScanner::test_aws_access_key_leaked", "type": "Function", "lineno": 33}, {"nodeid": "tests/test_malicious_scenarios.py::TestSecretScanner::test_rsa_private_key_committed", "type": "Function", "lineno": 41}, {"nodeid": "tests/test_malicious_scenarios.py::TestSecretScanner::test_hardcoded_password_assignment", "type": "Function", "lineno": 49}, {"nodeid": "tests/test_malicious_scenarios.py::TestSecretScanner::test_ssn_in_mock_data", "type": "Function", "lineno": 56}, {"nodeid": "tests/test_malicious_scenarios.py::TestSecretScanner::test_internal_ip_hardcoded", "type": "Function", "lineno": 64}, {"nodeid": "tests/test_malicious_scenarios.py::TestSecretScanner::test_slack_bot_token_leaked", "type": "Function", "lineno": 71}, {"nodeid": "tests/test_malicious_scenarios.py::TestSecretScanner::test_safe_print_not_flagged", "type": "Function", "lineno": 79}]}, {"nodeid": "tests/test_malicious_scenarios.py::TestMaliciousScanner", "outcome": "passed", "result": [{"nodeid": "tests/test_malicious_scenarios.py::TestMaliciousScanner::test_reverse_shell_bash", "type": "Function", "lineno": 97}, {"nodeid": "tests/test_malicious_scenarios.py::TestMaliciousScanner::test_reverse_shell_netcat", "type": "Function", "lineno": 105}, {"nodeid": "tests/test_malicious_scenarios.py::TestMaliciousScanner::test_curl_pipe_to_bash", "type": "Function", "lineno": 113}, {"nodeid": "tests/test_malicious_scenarios.py::TestMaliciousScanner::test_destructive_rm_rf", "type": "Function", "lineno": 120}, {"nodeid": "tests/test_malicious_scenarios.py::TestMaliciousScanner::test_base64_obfuscated_payload", "type": "Function", "lineno": 128}, {"nodeid": "tests/test_malicious_scenarios.py::TestMaliciousScanner::test_cron_persistence", "type": "Function", "lineno": 135}, {"nodeid": "tests/test_malicious_scenarios.py::TestMaliciousScanner::test_ssh_backdoor", "type": "Function", "lineno": 142}]}, {"nodeid": "tests/test_malicious_scenarios.py::TestIaCScanner", "outcome": "passed", "result": [{"nodeid": "tests/test_malicious_scenarios.py::TestIaCScanner::test_public_s3_bucket", "type": "Function", "lineno": 157}, {"nodeid": "tests/test_malicious_scenarios.py::TestIaCScanner::test_open_security_group", "type": "Function", "lineno": 165}, {"nodeid": "tests/test_malicious_scenarios.py::TestIaCScanner::test_privileged_kubernetes_pod", "type": "Function", "lineno": 172}, {"nodeid": "tests/test_malicious_scenarios.py::TestIaCScanner::test_kubernetes_root_user", "type": "Function", "lineno": 180}, {"nodeid": "tests/test_malicious_scenarios.py::TestIaCScanner::test_safe_terraform_private_bucket", "type": "Function", "lineno": 187}]}, {"nodeid": "tests/test_malicious_scenarios.py", "outcome": "passed", "result": [{"nodeid": "tests/test_malicious_scenarios.py::TestSecretScanner", "type": "Class"}, {"nodeid": "tests/test_malicious_scenarios.py::TestMaliciousScanner", "type": "Class"}, {"nodeid": "tests/test_malicious_scenarios.py::TestIaCScanner", "type": "Class"}]}, {"nodeid": "tests/test_scanners.py", "outcome": "passed", "result": [{"nodeid": "tests/test_scanners.py::test_secret_scanner_finds_github_pat", "type": "Function", "lineno": 4}, {"nodeid": "tests/test_scanners.py::test_secret_scanner_ignores_safe_line", "type": "Function", "lineno": 13}, {"nodeid": "tests/test_scanners.py::test_malicious_scanner_finds_reverse_shell", "type": "Function", "lineno": 20}, {"nodeid": "tests/test_scanners.py::test_sca_scanner_finds_banned_package", "type": "Function", "lineno": 29}]}, {"nodeid": "tests", "outcome": "passed", "result": [{"nodeid": "tests/test_malicious_scenarios.py", "type": "Module"}, {"nodeid": "tests/test_scanners.py", "type": "Module"}]}], "tests": [{"nodeid": "tests/test_malicious_scenarios.py::TestSecretScanner::test_aws_access_key_leaked", "lineno": 33, "outcome": "passed", "keywords": ["test_aws_access_key_leaked", "TestSecretScanner", "test_malicious_scenarios.py", "tests", "gitcheck", ""], "setup": {"duration": 0.00022199899990482663, "outcome": "passed"}, "call": {"duration": 0.000669428000037442, "outcome": "passed"}, "teardown": {"duration": 7.901000003585068e-05, "outcome": "passed"}}, {"nodeid": "tests/test_malicious_scenarios.py::TestSecretScanner::test_rsa_private_key_committed", "lineno": 41, "outcome": "passed", "keywords": ["test_rsa_private_key_committed", "TestSecretScanner", "test_malicious_scenarios.py", "tests", "gitcheck", ""], "setup": {"duration": 9.377899982609961e-05, "outcome": "passed"}, "call": {"duration": 7.659299990336876e-05, "outcome": "passed"}, "teardown": {"duration": 5.6096999969668104e-05, "outcome": "passed"}}, {"nodeid": "tests/test_malicious_scenarios.py::TestSecretScanner::test_hardcoded_password_assignment", "lineno": 49, "outcome": "passed", "keywords": ["test_hardcoded_password_assignment", "TestSecretScanner", "test_malicious_scenarios.py", "tests", "gitcheck", ""], "setup": {"duration": 7.727299998805393e-05, "outcome": "passed"}, "call": {"duration": 7.05340000877186e-05, "outcome": "passed"}, "teardown": {"duration": 5.1856000027328264e-05, "outcome": "passed"}}, {"nodeid": "tests/test_malicious_scenarios.py::TestSecretScanner::test_ssn_in_mock_data", "lineno": 56, "outcome": "passed", "keywords": ["test_ssn_in_mock_data", "TestSecretScanner", "test_malicious_scenarios.py", "tests", "gitcheck", ""], "setup": {"duration": 7.525799992436077e-05, "outcome": "passed"}, "call": {"duration": 7.359599999290367e-05, "outcome": "passed"}, "teardown": {"duration": 5.4918000159887015e-05, "outcome": "passed"}}, {"nodeid": "tests/test_malicious_scenarios.py::TestSecretScanner::test_internal_ip_hardcoded", "lineno": 64, "outcome": "passed", "keywords": ["test_internal_ip_hardcoded", "TestSecretScanner", "test_malicious_scenarios.py", "tests", "gitcheck", ""], "setup": {"duration": 8.440400006293203e-05, "outcome": "passed"}, "call": {"duration": 8.479600001010112e-05, "outcome": "passed"}, "teardown": {"duration": 5.547899991142913e-05, "outcome": "passed"}}, {"nodeid": "tests/test_malicious_scenarios.py::TestSecretScanner::test_slack_bot_token_leaked", "lineno": 71, "outcome": "passed", "keywords": ["test_slack_bot_token_leaked", "TestSecretScanner", "test_malicious_scenarios.py", "tests", "gitcheck", ""], "setup": {"duration": 7.227800006148755e-05, "outcome": "passed"}, "call": {"duration": 6.814200014559901e-05, "outcome": "passed"}, "teardown": {"duration": 5.337000015970261e-05, "outcome": "passed"}}, {"nodeid": "tests/test_malicious_scenarios.py::TestSecretScanner::test_safe_print_not_flagged", "lineno": 79, "outcome": "passed", "keywords": ["test_safe_print_not_flagged", "TestSecretScanner", "test_malicious_scenarios.py", "tests", "gitcheck", ""], "setup": {"duration": 6.846599990240065e-05, "outcome": "passed"}, "call": {"duration": 7.766599992464762e-05, "outcome": "passed"}, "teardown": {"duration": 5.126199994265335e-05, "outcome": "passed"}}, {"nodeid": "tests/test_malicious_scenarios.py::TestMaliciousScanner::test_reverse_shell_bash", "lineno": 97, "outcome": "passed", "keywords": ["test_reverse_shell_bash", "TestMaliciousScanner", "test_malicious_scenarios.py", "tests", "gitcheck", ""], "setup": {"duration": 7.104899987098179e-05, "outcome": "passed"}, "call": {"duration": 0.0013254650000362744, "outcome": "passed"}, "teardown": {"duration": 7.499399998778244e-05, "outcome": "passed"}}, {"nodeid": "tests/test_malicious_scenarios.py::TestMaliciousScanner::test_reverse_shell_netcat", "lineno": 105, "outcome": "passed", "keywords": ["test_reverse_shell_netcat", "TestMaliciousScanner", "test_malicious_scenarios.py", "tests", "gitcheck", ""], "setup": {"duration": 8.194199995159579e-05, "outcome": "passed"}, "call": {"duration": 7.872000014685909e-05, "outcome": "passed"}, "teardown": {"duration": 5.725400001210801e-05, "outcome": "passed"}}, {"nodeid": "tests/test_malicious_scenarios.py::TestMaliciousScanner::test_curl_pipe_to_bash", "lineno": 113, "outcome": "passed", "keywords": ["test_curl_pipe_to_bash", "TestMaliciousScanner", "test_malicious_scenarios.py", "tests", "gitcheck", ""], "setup": {"duration": 8.766299993112625e-05, "outcome": "passed"}, "call": {"duration": 7.119299993973982e-05, "outcome": "passed"}, "teardown": {"duration": 5.4862000069988426e-05, "outcome": "passed"}}, {"nodeid": "tests/test_malicious_scenarios.py::TestMaliciousScanner::test_destructive_rm_rf", "lineno": 120, "outcome": "passed", "keywords": ["test_destructive_rm_rf", "TestMaliciousScanner", "test_malicious_scenarios.py", "tests", "gitcheck", ""], "setup": {"duration": 7.044300014058535e-05, "outcome": "passed"}, "call": {"duration": 6.109800006015575e-05, "outcome": "passed"}, "teardown": {"duration": 4.793700009031454e-05, "outcome": "passed"}}, {"nodeid": "tests/test_malicious_scenarios.py::TestMaliciousScanner::test_base64_obfuscated_payload", "lineno": 128, "outcome": "passed", "keywords": ["test_base64_obfuscated_payload", "TestMaliciousScanner", "test_malicious_scenarios.py", "tests", "gitcheck", ""], "setup": {"duration": 6.663499993919686e-05, "outcome": "passed"}, "call": {"duration": 5.990999989080592e-05, "outcome": "passed"}, "teardown": {"duration": 4.6642000143037876e-05, "outcome": "passed"}}, {"nodeid": "tests/test_malicious_scenarios.py::TestMaliciousScanner::test_cron_persistence", "lineno": 135, "outcome": "passed", "keywords": ["test_cron_persistence", "TestMaliciousScanner", "test_malicious_scenarios.py", "tests", "gitcheck", ""], "setup": {"duration": 7.25389998024184e-05, "outcome": "passed"}, "call": {"duration": 7.284299999810173e-05, "outcome": "passed"}, "teardown": {"duration": 4.890600007456669e-05, "outcome": "passed"}}, {"nodeid": "tests/test_malicious_scenarios.py::TestMaliciousScanner::test_ssh_backdoor", "lineno": 142, "outcome": "passed", "keywords": ["test_ssh_backdoor", "TestMaliciousScanner", "test_malicious_scenarios.py", "tests", "gitcheck", ""], "setup": {"duration": 6.846700011919893e-05, "outcome": "passed"}, "call": {"duration": 6.0128000086479005e-05, "outcome": "passed"}, "teardown": {"duration": 4.68000000637403e-05, "outcome": "passed"}}, {"nodeid": "tests/test_malicious_scenarios.py::TestIaCScanner::test_public_s3_bucket", "lineno": 157, "outcome": "passed", "keywords": ["test_public_s3_bucket", "TestIaCScanner", "test_malicious_scenarios.py", "tests", "gitcheck", ""], "setup": {"duration": 6.209299999682116e-05, "outcome": "passed"}, "call": {"duration": 0.00021094800013088388, "outcome": "passed"}, "teardown": {"duration": 5.646299996442394e-05, "outcome": "passed"}}, {"nodeid": "tests/test_malicious_scenarios.py::TestIaCScanner::test_open_security_group", "lineno": 165, "outcome": "passed", "keywords": ["test_open_security_group", "TestIaCScanner", "test_malicious_scenarios.py", "tests", "gitcheck", ""], "setup": {"duration": 7.957399998304027e-05, "outcome": "passed"}, "call": {"duration": 6.051799982742523e-05, "outcome": "passed"}, "teardown": {"duration": 4.8266000021612854e-05, "outcome": "passed"}}, {"nodeid": "tests/test_malicious_scenarios.py::TestIaCScanner::test_privileged_kubernetes_pod", "lineno": 172, "outcome": "passed", "keywords": ["test_privileged_kubernetes_pod", "TestIaCScanner", "test_malicious_scenarios.py", "tests", "gitcheck", ""], "setup": {"duration": 6.423100012398208e-05, "outcome": "passed"}, "call": {"duration": 0.00013212399994699808, "outcome": "passed"}, "teardown": {"duration": 5.4954999995970866e-05, "outcome": "passed"}}, {"nodeid": "tests/test_malicious_scenarios.py::TestIaCScanner::test_kubernetes_root_user", "lineno": 180, "outcome": "passed", "keywords": ["test_kubernetes_root_user", "TestIaCScanner", "test_malicious_scenarios.py", "tests", "gitcheck", ""], "setup": {"duration": 6.934099997124576e-05, "outcome": "passed"}, "call": {"duration": 5.976199986434949e-05, "outcome": "passed"}, "teardown": {"duration": 5.134600019118807e-05, "outcome": "passed"}}, {"nodeid": "tests/test_malicious_scenarios.py::TestIaCScanner::test_safe_terraform_private_bucket", "lineno": 187, "outcome": "passed", "keywords": ["test_safe_terraform_private_bucket", "TestIaCScanner", "test_malicious_scenarios.py", "tests", "gitcheck", ""], "setup": {"duration": 6.491299996014277e-05, "outcome": "passed"}, "call": {"duration": 5.6485999948563403e-05, "outcome": "passed"}, "teardown": {"duration": 5.386800012274762e-05, "outcome": "passed"}}, {"nodeid": "tests/test_scanners.py::test_secret_scanner_finds_github_pat", "lineno": 4, "outcome": "passed", "keywords": ["test_secret_scanner_finds_github_pat", "test_scanners.py", "tests", "gitcheck", ""], "setup": {"duration": 6.714899996040913e-05, "outcome": "passed"}, "call": {"duration": 6.80380001085723e-05, "outcome": "passed"}, "teardown": {"duration": 5.3290000096239964e-05, "outcome": "passed"}}, {"nodeid": "tests/test_scanners.py::test_secret_scanner_ignores_safe_line", "lineno": 13, "outcome": "passed", "keywords": ["test_secret_scanner_ignores_safe_line", "test_scanners.py", "tests", "gitcheck", ""], "setup": {"duration": 6.735600004503794e-05, "outcome": "passed"}, "call": {"duration": 6.282200001805904e-05, "outcome": "passed"}, "teardown": {"duration": 4.758599993692769e-05, "outcome": "passed"}}, {"nodeid": "tests/test_scanners.py::test_malicious_scanner_finds_reverse_shell", "lineno": 20, "outcome": "passed", "keywords": ["test_malicious_scanner_finds_reverse_shell", "test_scanners.py", "tests", "gitcheck", ""], "setup": {"duration": 6.57289999708155e-05, "outcome": "passed"}, "call": {"duration": 6.844100016678567e-05, "outcome": "passed"}, "teardown": {"duration": 4.645299986805185e-05, "outcome": "passed"}}, {"nodeid": "tests/test_scanners.py::test_sca_scanner_finds_banned_package", "lineno": 29, "outcome": "passed", "keywords": ["test_sca_scanner_finds_banned_package", "test_scanners.py", "tests", "gitcheck", ""], "setup": {"duration": 6.193700005496794e-05, "outcome": "passed"}, "call": {"duration": 0.00011577399982343195, "outcome": "passed"}, "teardown": {"duration": 5.712300003324344e-05, "outcome": "passed"}}]}